{"paula": {"@version": "1.0", "header": {"@paula_id": "AP.25.pambo_origSeg"}, "markList": {"@xmlns:xlink": "http://www.w3.org/1999/xlink", "@type": "origSeg", "@xml:base": "AP.25.pambo.tok.xml", "mark": [{"@id": "orig_1", "@xlink:href": "#xpointer(id('tok_1')/range-to(id('tok_3')))"}, {"@id": "orig_4", "@xlink:href": "#tok_4"}, {"@id": "orig_5", "@xlink:href": "#tok_5"}, {"@id": "orig_6", "@xlink:href": "#tok_6"}, {"@id": "orig_7", "@xlink:href": "#tok_7"}, {"@id": "orig_8", "@xlink:href": "#tok_8"}, {"@id": "orig_9", "@xlink:href": "#tok_9"}, {"@id": "orig_10", "@xlink:href": "#tok_10"}, {"@id": "orig_11", "@xlink:href": "#tok_11"}, {"@id": "orig_12", "@xlink:href": "#tok_12"}, {"@id": "orig_13", "@xlink:href": "#tok_13"}, {"@id": "orig_14", "@xlink:href": "#tok_14"}, {"@id": "orig_15", "@xlink:href": "#tok_15"}, {"@id": "orig_16", "@xlink:href": "#tok_16"}, {"@id": "orig_17", "@xlink:href": "#tok_17"}, {"@id": "orig_18", "@xlink:href": "#tok_18"}, {"@id": "orig_19", "@xlink:href": "#tok_19"}, {"@id": "orig_20", "@xlink:href": "#tok_20"}, {"@id": "orig_21", "@xlink:href": "#xpointer(id('tok_21')/range-to(id('tok_22')))"}, {"@id": "orig_23", "@xlink:href": "#tok_23"}, {"@id": "orig_24", "@xlink:href": "#tok_24"}, {"@id": "orig_25", "@xlink:href": "#tok_25"}, {"@id": "orig_26", "@xlink:href": "#tok_26"}, {"@id": "orig_27", "@xlink:href": "#xpointer(id('tok_27')/range-to(id('tok_28')))"}, {"@id": "orig_29", "@xlink:href": "#tok_29"}, {"@id": "orig_30", "@xlink:href": "#tok_30"}, {"@id": "orig_31", "@xlink:href": "#tok_31"}, {"@id": "orig_32", "@xlink:href": "#tok_32"}, {"@id": "orig_33", "@xlink:href": "#tok_33"}, {"@id": "orig_34", "@xlink:href": "#tok_34"}, {"@id": "orig_35", "@xlink:href": "#tok_35"}, {"@id": "orig_36", "@xlink:href": "#tok_36"}, {"@id": "orig_37", "@xlink:href": "#tok_37"}, {"@id": "orig_38", "@xlink:href": "#tok_38"}, {"@id": "orig_39", "@xlink:href": "#tok_39"}, {"@id": "orig_40", "@xlink:href": "#tok_40"}, {"@id": "orig_41", "@xlink:href": "#tok_41"}, {"@id": "orig_42", "@xlink:href": "#tok_42"}, {"@id": "orig_43", "@xlink:href": "#tok_43"}, {"@id": "orig_44", "@xlink:href": "#tok_44"}, {"@id": "orig_45", "@xlink:href": "#tok_45"}, {"@id": "orig_46", "@xlink:href": "#tok_46"}, {"@id": "orig_47", "@xlink:href": "#tok_47"}, {"@id": "orig_48", "@xlink:href": "#tok_48"}, {"@id": "orig_49", "@xlink:href": "#tok_49"}, {"@id": "orig_50", "@xlink:href": "#tok_50"}, {"@id": "orig_51", "@xlink:href": "#xpointer(id('tok_51')/range-to(id('tok_52')))"}, {"@id": "orig_53", "@xlink:href": "#tok_53"}, {"@id": "orig_54", "@xlink:href": "#tok_54"}, {"@id": "orig_55", "@xlink:href": "#tok_55"}, {"@id": "orig_56", "@xlink:href": "#tok_56"}, {"@id": "orig_57", "@xlink:href": "#tok_57"}, {"@id": "orig_58", "@xlink:href": "#tok_58"}, {"@id": "orig_59", "@xlink:href": "#xpointer(id('tok_59')/range-to(id('tok_60')))"}, {"@id": "orig_61", "@xlink:href": "#tok_61"}, {"@id": "orig_62", "@xlink:href": "#tok_62"}, {"@id": "orig_63", "@xlink:href": "#tok_63"}, {"@id": "orig_64", "@xlink:href": "#xpointer(id('tok_64')/range-to(id('tok_65')))"}, {"@id": "orig_66", "@xlink:href": "#tok_66"}, {"@id": "orig_67", "@xlink:href": "#tok_67"}, {"@id": "orig_68", "@xlink:href": "#tok_68"}]}}}