{"paula": {"@version": "1.0", "header": {"@paula_id": "sahidica.Mark_13_translationSeg"}, "markList": {"@xmlns:xlink": "http://www.w3.org/1999/xlink", "@type": "translationSeg", "@xml:base": "sahidica.Mark_13.tok.xml", "mark": [{"@id": "translation_1", "@xlink:href": "#xpointer(id('tok_1')/range-to(id('tok_35')))"}, {"@id": "translation_36", "@xlink:href": "#xpointer(id('tok_36')/range-to(id('tok_70')))"}, {"@id": "translation_71", "@xlink:href": "#xpointer(id('tok_71')/range-to(id('tok_105')))"}, {"@id": "translation_106", "@xlink:href": "#xpointer(id('tok_106')/range-to(id('tok_132')))"}, {"@id": "translation_133", "@xlink:href": "#xpointer(id('tok_133')/range-to(id('tok_152')))"}, {"@id": "translation_153", "@xlink:href": "#xpointer(id('tok_153')/range-to(id('tok_175')))"}, {"@id": "translation_176", "@xlink:href": "#xpointer(id('tok_176')/range-to(id('tok_202')))"}, {"@id": "translation_203", "@xlink:href": "#xpointer(id('tok_203')/range-to(id('tok_234')))"}, {"@id": "translation_235", "@xlink:href": "#xpointer(id('tok_235')/range-to(id('tok_281')))"}, {"@id": "translation_282", "@xlink:href": "#xpointer(id('tok_282')/range-to(id('tok_291')))"}, {"@id": "translation_292", "@xlink:href": "#xpointer(id('tok_292')/range-to(id('tok_347')))"}, {"@id": "translation_348", "@xlink:href": "#xpointer(id('tok_348')/range-to(id('tok_381')))"}, {"@id": "translation_382", "@xlink:href": "#xpointer(id('tok_382')/range-to(id('tok_405')))"}, {"@id": "translation_406", "@xlink:href": "#xpointer(id('tok_406')/range-to(id('tok_447')))"}, {"@id": "translation_448", "@xlink:href": "#xpointer(id('tok_448')/range-to(id('tok_471')))"}, {"@id": "translation_472", "@xlink:href": "#xpointer(id('tok_472')/range-to(id('tok_489')))"}, {"@id": "translation_490", "@xlink:href": "#xpointer(id('tok_490')/range-to(id('tok_505')))"}, {"@id": "translation_506", "@xlink:href": "#xpointer(id('tok_506')/range-to(id('tok_516')))"}, {"@id": "translation_517", "@xlink:href": "#xpointer(id('tok_517')/range-to(id('tok_559')))"}, {"@id": "translation_560", "@xlink:href": "#xpointer(id('tok_560')/range-to(id('tok_590')))"}, {"@id": "translation_591", "@xlink:href": "#xpointer(id('tok_591')/range-to(id('tok_614')))"}, {"@id": "translation_615", "@xlink:href": "#xpointer(id('tok_615')/range-to(id('tok_648')))"}, {"@id": "translation_649", "@xlink:href": "#xpointer(id('tok_649')/range-to(id('tok_665')))"}, {"@id": "translation_666", "@xlink:href": "#xpointer(id('tok_666')/range-to(id('tok_693')))"}, {"@id": "translation_694", "@xlink:href": "#xpointer(id('tok_694')/range-to(id('tok_713')))"}, {"@id": "translation_714", "@xlink:href": "#xpointer(id('tok_714')/range-to(id('tok_739')))"}, {"@id": "translation_740", "@xlink:href": "#xpointer(id('tok_740')/range-to(id('tok_772')))"}, {"@id": "translation_773", "@xlink:href": "#xpointer(id('tok_773')/range-to(id('tok_808')))"}, {"@id": "translation_809", "@xlink:href": "#xpointer(id('tok_809')/range-to(id('tok_839')))"}, {"@id": "translation_840", "@xlink:href": "#xpointer(id('tok_840')/range-to(id('tok_858')))"}, {"@id": "translation_859", "@xlink:href": "#xpointer(id('tok_859')/range-to(id('tok_877')))"}, {"@id": "translation_878", "@xlink:href": "#xpointer(id('tok_878')/range-to(id('tok_906')))"}, {"@id": "translation_907", "@xlink:href": "#xpointer(id('tok_907')/range-to(id('tok_927')))"}, {"@id": "translation_928", "@xlink:href": "#xpointer(id('tok_928')/range-to(id('tok_980')))"}, {"@id": "translation_981", "@xlink:href": "#xpointer(id('tok_981')/range-to(id('tok_1026')))"}, {"@id": "translation_1027", "@xlink:href": "#xpointer(id('tok_1027')/range-to(id('tok_1042')))"}]}}}