{"paula": {"@version": "1.0", "header": {"@paula_id": "sahidica.Mark_15_verse"}, "featList": {"@xmlns:xlink": "http://www.w3.org/1999/xlink", "@type": "verse", "@xml:base": "sahidica.Mark_15.verseSeg.xml", "feat": [{"@xlink:href": "#verse_1", "@value": "Mark 15:1"}, {"@xlink:href": "#verse_42", "@value": "Mark 15:2"}, {"@xlink:href": "#verse_75", "@value": "Mark 15:3"}, {"@xlink:href": "#verse_85", "@value": "Mark 15:4"}, {"@xlink:href": "#verse_109", "@value": "Mark 15:5"}, {"@xlink:href": "#verse_122", "@value": "Mark 15:6"}, {"@xlink:href": "#verse_144", "@value": "Mark 15:7"}, {"@xlink:href": "#verse_176", "@value": "Mark 15:8"}, {"@xlink:href": "#verse_199", "@value": "Mark 15:9"}, {"@xlink:href": "#verse_226", "@value": "Mark 15:10"}, {"@xlink:href": "#verse_243", "@value": "Mark 15:11"}, {"@xlink:href": "#verse_268", "@value": "Mark 15:12"}, {"@xlink:href": "#verse_296", "@value": "Mark 15:13"}, {"@xlink:href": "#verse_309", "@value": "Mark 15:14"}, {"@xlink:href": "#verse_348", "@value": "Mark 15:15"}, {"@xlink:href": "#verse_386", "@value": "Mark 15:16"}, {"@xlink:href": "#verse_412", "@value": "Mark 15:17"}, {"@xlink:href": "#verse_437", "@value": "Mark 15:18"}, {"@xlink:href": "#verse_453", "@value": "Mark 15:19"}, {"@xlink:href": "#verse_486", "@value": "Mark 15:20"}, {"@xlink:href": "#verse_527", "@value": "Mark 15:21"}, {"@xlink:href": "#verse_562", "@value": "Mark 15:22"}, {"@xlink:href": "#verse_586", "@value": "Mark 15:23"}, {"@xlink:href": "#verse_607", "@value": "Mark 15:24"}, {"@xlink:href": "#verse_637", "@value": "Mark 15:25"}, {"@xlink:href": "#verse_651", "@value": "Mark 15:26"}, {"@xlink:href": "#verse_663", "@value": "Mark 15:27"}, {"@xlink:href": "#verse_682", "@value": "Mark 15:28"}, {"@xlink:href": "#verse_685", "@value": "Mark 15:29"}, {"@xlink:href": "#verse_725", "@value": "Mark 15:30"}, {"@xlink:href": "#verse_736", "@value": "Mark 15:31"}, {"@xlink:href": "#verse_775", "@value": "Mark 15:32"}, {"@xlink:href": "#verse_818", "@value": "Mark 15:33"}, {"@xlink:href": "#verse_842", "@value": "Mark 15:34"}, {"@xlink:href": "#verse_887", "@value": "Mark 15:35"}, {"@xlink:href": "#verse_913", "@value": "Mark 15:36"}, {"@xlink:href": "#verse_956", "@value": "Mark 15:37"}, {"@xlink:href": "#verse_970", "@value": "Mark 15:38"}, {"@xlink:href": "#verse_989", "@value": "Mark 15:39"}, {"@xlink:href": "#verse_1024", "@value": "Mark 15:40"}, {"@xlink:href": "#verse_1062", "@value": "Mark 15:41"}, {"@xlink:href": "#verse_1094", "@value": "Mark 15:42"}, {"@xlink:href": "#verse_1112", "@value": "Mark 15:43"}, {"@xlink:href": "#verse_1162", "@value": "Mark 15:44"}, {"@xlink:href": "#verse_1195", "@value": "Mark 15:45"}, {"@xlink:href": "#verse_1214", "@value": "Mark 15:46"}, {"@xlink:href": "#verse_1264", "@value": "Mark 15:47"}]}}}