{"paula": {"@version": "1.0", "header": {"@paula_id": "AP.216.besarion_tok"}, "markList": {"@xmlns:xlink": "http://www.w3.org/1999/xlink", "@type": "tok", "@xml:base": "AP.216.besarion.text.xml", "mark": [{"@id": "tok_1", "@xlink:href": "#xpointer(string-range(//body,'',1,1))"}, {"@id": "tok_2", "@xlink:href": "#xpointer(string-range(//body,'',3,1))"}, {"@id": "tok_3", "@xlink:href": "#xpointer(string-range(//body,'',5,3))"}, {"@id": "tok_4", "@xlink:href": "#xpointer(string-range(//body,'',9,1))"}, {"@id": "tok_5", "@xlink:href": "#xpointer(string-range(//body,'',11,3))"}, {"@id": "tok_6", "@xlink:href": "#xpointer(string-range(//body,'',15,4))"}, {"@id": "tok_7", "@xlink:href": "#xpointer(string-range(//body,'',20,6))"}, {"@id": "tok_8", "@xlink:href": "#xpointer(string-range(//body,'',27,2))"}, {"@id": "tok_9", "@xlink:href": "#xpointer(string-range(//body,'',30,2))"}, {"@id": "tok_10", "@xlink:href": "#xpointer(string-range(//body,'',33,5))"}, {"@id": "tok_11", "@xlink:href": "#xpointer(string-range(//body,'',39,1))"}, {"@id": "tok_12", "@xlink:href": "#xpointer(string-range(//body,'',41,3))"}, {"@id": "tok_13", "@xlink:href": "#xpointer(string-range(//body,'',45,4))"}, {"@id": "tok_14", "@xlink:href": "#xpointer(string-range(//body,'',50,5))"}, {"@id": "tok_15", "@xlink:href": "#xpointer(string-range(//body,'',56,1))"}, {"@id": "tok_16", "@xlink:href": "#xpointer(string-range(//body,'',58,2))"}, {"@id": "tok_17", "@xlink:href": "#xpointer(string-range(//body,'',61,2))"}, {"@id": "tok_18", "@xlink:href": "#xpointer(string-range(//body,'',64,1))"}, {"@id": "tok_19", "@xlink:href": "#xpointer(string-range(//body,'',66,4))"}, {"@id": "tok_20", "@xlink:href": "#xpointer(string-range(//body,'',71,2))"}, {"@id": "tok_21", "@xlink:href": "#xpointer(string-range(//body,'',74,6))"}, {"@id": "tok_22", "@xlink:href": "#xpointer(string-range(//body,'',81,1))"}, {"@id": "tok_23", "@xlink:href": "#xpointer(string-range(//body,'',83,6))"}, {"@id": "tok_24", "@xlink:href": "#xpointer(string-range(//body,'',90,4))"}, {"@id": "tok_25", "@xlink:href": "#xpointer(string-range(//body,'',95,1))"}, {"@id": "tok_26", "@xlink:href": "#xpointer(string-range(//body,'',97,2))"}, {"@id": "tok_27", "@xlink:href": "#xpointer(string-range(//body,'',100,5))"}, {"@id": "tok_28", "@xlink:href": "#xpointer(string-range(//body,'',106,1))"}, {"@id": "tok_29", "@xlink:href": "#xpointer(string-range(//body,'',108,1))"}, {"@id": "tok_30", "@xlink:href": "#xpointer(string-range(//body,'',110,2))"}, {"@id": "tok_31", "@xlink:href": "#xpointer(string-range(//body,'',113,4))"}, {"@id": "tok_32", "@xlink:href": "#xpointer(string-range(//body,'',118,1))"}, {"@id": "tok_33", "@xlink:href": "#xpointer(string-range(//body,'',120,1))"}, {"@id": "tok_34", "@xlink:href": "#xpointer(string-range(//body,'',122,3))"}, {"@id": "tok_35", "@xlink:href": "#xpointer(string-range(//body,'',126,9))"}, {"@id": "tok_36", "@xlink:href": "#xpointer(string-range(//body,'',136,2))"}, {"@id": "tok_37", "@xlink:href": "#xpointer(string-range(//body,'',139,2))"}, {"@id": "tok_38", "@xlink:href": "#xpointer(string-range(//body,'',142,5))"}, {"@id": "tok_39", "@xlink:href": "#xpointer(string-range(//body,'',148,2))"}, {"@id": "tok_40", "@xlink:href": "#xpointer(string-range(//body,'',151,4))"}, {"@id": "tok_41", "@xlink:href": "#xpointer(string-range(//body,'',156,2))"}, {"@id": "tok_42", "@xlink:href": "#xpointer(string-range(//body,'',159,3))"}, {"@id": "tok_43", "@xlink:href": "#xpointer(string-range(//body,'',163,1))"}, {"@id": "tok_44", "@xlink:href": "#xpointer(string-range(//body,'',165,2))"}, {"@id": "tok_45", "@xlink:href": "#xpointer(string-range(//body,'',168,5))"}, {"@id": "tok_46", "@xlink:href": "#xpointer(string-range(//body,'',174,2))"}, {"@id": "tok_47", "@xlink:href": "#xpointer(string-range(//body,'',177,1))"}, {"@id": "tok_48", "@xlink:href": "#xpointer(string-range(//body,'',179,1))"}, {"@id": "tok_49", "@xlink:href": "#xpointer(string-range(//body,'',181,5))"}, {"@id": "tok_50", "@xlink:href": "#xpointer(string-range(//body,'',187,4))"}, {"@id": "tok_51", "@xlink:href": "#xpointer(string-range(//body,'',192,1))"}, {"@id": "tok_52", "@xlink:href": "#xpointer(string-range(//body,'',194,2))"}, {"@id": "tok_53", "@xlink:href": "#xpointer(string-range(//body,'',197,2))"}, {"@id": "tok_54", "@xlink:href": "#xpointer(string-range(//body,'',200,2))"}, {"@id": "tok_55", "@xlink:href": "#xpointer(string-range(//body,'',203,3))"}, {"@id": "tok_56", "@xlink:href": "#xpointer(string-range(//body,'',207,2))"}, {"@id": "tok_57", "@xlink:href": "#xpointer(string-range(//body,'',210,1))"}, {"@id": "tok_58", "@xlink:href": "#xpointer(string-range(//body,'',212,3))"}, {"@id": "tok_59", "@xlink:href": "#xpointer(string-range(//body,'',216,1))"}, {"@id": "tok_60", "@xlink:href": "#xpointer(string-range(//body,'',218,4))"}, {"@id": "tok_61", "@xlink:href": "#xpointer(string-range(//body,'',223,2))"}, {"@id": "tok_62", "@xlink:href": "#xpointer(string-range(//body,'',226,1))"}, {"@id": "tok_63", "@xlink:href": "#xpointer(string-range(//body,'',228,4))"}, {"@id": "tok_64", "@xlink:href": "#xpointer(string-range(//body,'',233,2))"}, {"@id": "tok_65", "@xlink:href": "#xpointer(string-range(//body,'',236,4))"}, {"@id": "tok_66", "@xlink:href": "#xpointer(string-range(//body,'',241,5))"}, {"@id": "tok_67", "@xlink:href": "#xpointer(string-range(//body,'',247,1))"}, {"@id": "tok_68", "@xlink:href": "#xpointer(string-range(//body,'',249,5))"}, {"@id": "tok_69", "@xlink:href": "#xpointer(string-range(//body,'',255,2))"}, {"@id": "tok_70", "@xlink:href": "#xpointer(string-range(//body,'',258,1))"}, {"@id": "tok_71", "@xlink:href": "#xpointer(string-range(//body,'',260,2))"}, {"@id": "tok_72", "@xlink:href": "#xpointer(string-range(//body,'',263,2))"}, {"@id": "tok_73", "@xlink:href": "#xpointer(string-range(//body,'',266,1))"}, {"@id": "tok_74", "@xlink:href": "#xpointer(string-range(//body,'',268,1))"}, {"@id": "tok_75", "@xlink:href": "#xpointer(string-range(//body,'',270,4))"}, {"@id": "tok_76", "@xlink:href": "#xpointer(string-range(//body,'',275,1))"}, {"@id": "tok_77", "@xlink:href": "#xpointer(string-range(//body,'',277,2))"}, {"@id": "tok_78", "@xlink:href": "#xpointer(string-range(//body,'',280,2))"}, {"@id": "tok_79", "@xlink:href": "#xpointer(string-range(//body,'',283,1))"}, {"@id": "tok_80", "@xlink:href": "#xpointer(string-range(//body,'',285,2))"}, {"@id": "tok_81", "@xlink:href": "#xpointer(string-range(//body,'',288,3))"}, {"@id": "tok_82", "@xlink:href": "#xpointer(string-range(//body,'',292,2))"}, {"@id": "tok_83", "@xlink:href": "#xpointer(string-range(//body,'',295,4))"}, {"@id": "tok_84", "@xlink:href": "#xpointer(string-range(//body,'',300,2))"}, {"@id": "tok_85", "@xlink:href": "#xpointer(string-range(//body,'',303,2))"}, {"@id": "tok_86", "@xlink:href": "#xpointer(string-range(//body,'',306,6))"}, {"@id": "tok_87", "@xlink:href": "#xpointer(string-range(//body,'',313,3))"}, {"@id": "tok_88", "@xlink:href": "#xpointer(string-range(//body,'',317,3))"}, {"@id": "tok_89", "@xlink:href": "#xpointer(string-range(//body,'',321,4))"}, {"@id": "tok_90", "@xlink:href": "#xpointer(string-range(//body,'',326,1))"}, {"@id": "tok_91", "@xlink:href": "#xpointer(string-range(//body,'',328,1))"}, {"@id": "tok_92", "@xlink:href": "#xpointer(string-range(//body,'',330,2))"}, {"@id": "tok_93", "@xlink:href": "#xpointer(string-range(//body,'',333,2))"}, {"@id": "tok_94", "@xlink:href": "#xpointer(string-range(//body,'',336,2))"}, {"@id": "tok_95", "@xlink:href": "#xpointer(string-range(//body,'',339,2))"}, {"@id": "tok_96", "@xlink:href": "#xpointer(string-range(//body,'',342,1))"}, {"@id": "tok_97", "@xlink:href": "#xpointer(string-range(//body,'',344,2))"}, {"@id": "tok_98", "@xlink:href": "#xpointer(string-range(//body,'',347,7))"}, {"@id": "tok_99", "@xlink:href": "#xpointer(string-range(//body,'',355,2))"}, {"@id": "tok_100", "@xlink:href": "#xpointer(string-range(//body,'',358,5))"}, {"@id": "tok_101", "@xlink:href": "#xpointer(string-range(//body,'',364,3))"}, {"@id": "tok_102", "@xlink:href": "#xpointer(string-range(//body,'',368,1))"}, {"@id": "tok_103", "@xlink:href": "#xpointer(string-range(//body,'',370,2))"}, {"@id": "tok_104", "@xlink:href": "#xpointer(string-range(//body,'',373,5))"}, {"@id": "tok_105", "@xlink:href": "#xpointer(string-range(//body,'',379,2))"}, {"@id": "tok_106", "@xlink:href": "#xpointer(string-range(//body,'',382,6))"}, {"@id": "tok_107", "@xlink:href": "#xpointer(string-range(//body,'',389,1))"}, {"@id": "tok_108", "@xlink:href": "#xpointer(string-range(//body,'',391,3))"}, {"@id": "tok_109", "@xlink:href": "#xpointer(string-range(//body,'',395,4))"}, {"@id": "tok_110", "@xlink:href": "#xpointer(string-range(//body,'',400,1))"}, {"@id": "tok_111", "@xlink:href": "#xpointer(string-range(//body,'',402,2))"}, {"@id": "tok_112", "@xlink:href": "#xpointer(string-range(//body,'',405,2))"}, {"@id": "tok_113", "@xlink:href": "#xpointer(string-range(//body,'',408,2))"}, {"@id": "tok_114", "@xlink:href": "#xpointer(string-range(//body,'',411,5))"}, {"@id": "tok_115", "@xlink:href": "#xpointer(string-range(//body,'',417,2))"}, {"@id": "tok_116", "@xlink:href": "#xpointer(string-range(//body,'',420,2))"}, {"@id": "tok_117", "@xlink:href": "#xpointer(string-range(//body,'',423,1))"}, {"@id": "tok_118", "@xlink:href": "#xpointer(string-range(//body,'',425,3))"}, {"@id": "tok_119", "@xlink:href": "#xpointer(string-range(//body,'',429,4))"}, {"@id": "tok_120", "@xlink:href": "#xpointer(string-range(//body,'',434,1))"}, {"@id": "tok_121", "@xlink:href": "#xpointer(string-range(//body,'',436,4))"}, {"@id": "tok_122", "@xlink:href": "#xpointer(string-range(//body,'',441,2))"}, {"@id": "tok_123", "@xlink:href": "#xpointer(string-range(//body,'',444,2))"}, {"@id": "tok_124", "@xlink:href": "#xpointer(string-range(//body,'',447,2))"}, {"@id": "tok_125", "@xlink:href": "#xpointer(string-range(//body,'',450,2))"}, {"@id": "tok_126", "@xlink:href": "#xpointer(string-range(//body,'',453,2))"}, {"@id": "tok_127", "@xlink:href": "#xpointer(string-range(//body,'',456,4))"}, {"@id": "tok_128", "@xlink:href": "#xpointer(string-range(//body,'',461,1))"}, {"@id": "tok_129", "@xlink:href": "#xpointer(string-range(//body,'',463,2))"}, {"@id": "tok_130", "@xlink:href": "#xpointer(string-range(//body,'',466,6))"}, {"@id": "tok_131", "@xlink:href": "#xpointer(string-range(//body,'',473,2))"}, {"@id": "tok_132", "@xlink:href": "#xpointer(string-range(//body,'',476,5))"}, {"@id": "tok_133", "@xlink:href": "#xpointer(string-range(//body,'',482,2))"}, {"@id": "tok_134", "@xlink:href": "#xpointer(string-range(//body,'',485,4))"}, {"@id": "tok_135", "@xlink:href": "#xpointer(string-range(//body,'',490,2))"}, {"@id": "tok_136", "@xlink:href": "#xpointer(string-range(//body,'',493,1))"}, {"@id": "tok_137", "@xlink:href": "#xpointer(string-range(//body,'',495,1))"}, {"@id": "tok_138", "@xlink:href": "#xpointer(string-range(//body,'',497,4))"}, {"@id": "tok_139", "@xlink:href": "#xpointer(string-range(//body,'',502,2))"}, {"@id": "tok_140", "@xlink:href": "#xpointer(string-range(//body,'',505,5))"}, {"@id": "tok_141", "@xlink:href": "#xpointer(string-range(//body,'',511,2))"}, {"@id": "tok_142", "@xlink:href": "#xpointer(string-range(//body,'',514,2))"}, {"@id": "tok_143", "@xlink:href": "#xpointer(string-range(//body,'',517,2))"}, {"@id": "tok_144", "@xlink:href": "#xpointer(string-range(//body,'',520,2))"}, {"@id": "tok_145", "@xlink:href": "#xpointer(string-range(//body,'',523,5))"}, {"@id": "tok_146", "@xlink:href": "#xpointer(string-range(//body,'',529,2))"}, {"@id": "tok_147", "@xlink:href": "#xpointer(string-range(//body,'',532,4))"}, {"@id": "tok_148", "@xlink:href": "#xpointer(string-range(//body,'',537,2))"}, {"@id": "tok_149", "@xlink:href": "#xpointer(string-range(//body,'',540,1))"}, {"@id": "tok_150", "@xlink:href": "#xpointer(string-range(//body,'',542,2))"}, {"@id": "tok_151", "@xlink:href": "#xpointer(string-range(//body,'',545,2))"}, {"@id": "tok_152", "@xlink:href": "#xpointer(string-range(//body,'',548,1))"}, {"@id": "tok_153", "@xlink:href": "#xpointer(string-range(//body,'',550,3))"}, {"@id": "tok_154", "@xlink:href": "#xpointer(string-range(//body,'',554,2))"}, {"@id": "tok_155", "@xlink:href": "#xpointer(string-range(//body,'',557,1))"}, {"@id": "tok_156", "@xlink:href": "#xpointer(string-range(//body,'',559,5))"}, {"@id": "tok_157", "@xlink:href": "#xpointer(string-range(//body,'',565,2))"}, {"@id": "tok_158", "@xlink:href": "#xpointer(string-range(//body,'',568,5))"}, {"@id": "tok_159", "@xlink:href": "#xpointer(string-range(//body,'',574,2))"}, {"@id": "tok_160", "@xlink:href": "#xpointer(string-range(//body,'',577,1))"}]}}}