{"paula": {"@version": "1.0", "header": {"@paula_id": "besa.to_thieving_nuns.annoSet"}, "structList": {"@xmlns:xlink": "http://www.w3.org/1999/xlink", "@type": "annoSet", "struct": {"@id": "anno_1", "rel": [{"@id": "rel_1", "@xlink:href": "besa.to_thieving_nuns.text.xml"}, {"@id": "rel_2", "@xlink:href": "besa.to_thieving_nuns.tok.xml"}, {"@id": "rel_3", "@xlink:href": "besa.to_thieving_nuns.origSeg_orig.xml"}, {"@id": "rel_4", "@xlink:href": "besa.to_thieving_nuns.origSeg.xml"}, {"@id": "rel_5", "@xlink:href": "besa.to_thieving_nuns.orig_groupSeg_orig_group.xml"}, {"@id": "rel_6", "@xlink:href": "besa.to_thieving_nuns.orig_groupSeg.xml"}, {"@id": "rel_7", "@xlink:href": "besa.to_thieving_nuns.norm_groupSeg_norm_group.xml"}, {"@id": "rel_8", "@xlink:href": "besa.to_thieving_nuns.norm_groupSeg.xml"}, {"@id": "rel_9", "@xlink:href": "besa.to_thieving_nuns.normSeg_norm.xml"}, {"@id": "rel_10", "@xlink:href": "besa.to_thieving_nuns.normSeg.xml"}, {"@id": "rel_11", "@xlink:href": "besa.to_thieving_nuns.morphSeg_morph.xml"}, {"@id": "rel_12", "@xlink:href": "besa.to_thieving_nuns.morphSeg.xml"}, {"@id": "rel_13", "@xlink:href": "besa.to_thieving_nuns.posSeg_pos.xml"}, {"@id": "rel_14", "@xlink:href": "besa.to_thieving_nuns.posSeg.xml"}, {"@id": "rel_15", "@xlink:href": "besa.to_thieving_nuns.langSeg_lang.xml"}, {"@id": "rel_16", "@xlink:href": "besa.to_thieving_nuns.langSeg.xml"}, {"@id": "rel_17", "@xlink:href": "besa.to_thieving_nuns.translationSeg_translation.xml"}, {"@id": "rel_18", "@xlink:href": "besa.to_thieving_nuns.translationSeg.xml"}, {"@id": "rel_19", "@xlink:href": "besa.to_thieving_nuns.hi_rendSeg_hi_rend.xml"}, {"@id": "rel_20", "@xlink:href": "besa.to_thieving_nuns.hi_rendSeg.xml"}, {"@id": "rel_21", "@xlink:href": "besa.to_thieving_nuns.noteSeg_note.xml"}, {"@id": "rel_22", "@xlink:href": "besa.to_thieving_nuns.noteSeg.xml"}, {"@id": "rel_23", "@xlink:href": "besa.to_thieving_nuns.lb_nSeg_lb_n.xml"}, {"@id": "rel_24", "@xlink:href": "besa.to_thieving_nuns.lb_nSeg.xml"}, {"@id": "rel_25", "@xlink:href": "besa.to_thieving_nuns.cb_nSeg_cb_n.xml"}, {"@id": "rel_26", "@xlink:href": "besa.to_thieving_nuns.cb_nSeg.xml"}, {"@id": "rel_27", "@xlink:href": "besa.to_thieving_nuns.pb_xml_idSeg_pb_xml_id.xml"}, {"@id": "rel_28", "@xlink:href": "besa.to_thieving_nuns.pb_xml_idSeg.xml"}, {"@id": "rel_29", "@xlink:href": "besa.to_thieving_nuns.p_nSeg_p_n.xml"}, {"@id": "rel_30", "@xlink:href": "besa.to_thieving_nuns.p_nSeg.xml"}]}}}}