{"paula": {"@version": "1.0", "header": {"@paula_id": "shenoute.fox_langSeg"}, "markList": {"@xmlns:xlink": "http://www.w3.org/1999/xlink", "@type": "langSeg", "@xml:base": "shenoute.fox.tok.xml", "mark": [{"@id": "lang_16", "@xlink:href": "#tok_16"}, {"@id": "lang_35", "@xlink:href": "#tok_35"}, {"@id": "lang_47", "@xlink:href": "#tok_47"}, {"@id": "lang_52", "@xlink:href": "#tok_52"}, {"@id": "lang_58", "@xlink:href": "#xpointer(id('tok_58')/range-to(id('tok_59')))"}, {"@id": "lang_61", "@xlink:href": "#tok_61"}, {"@id": "lang_71", "@xlink:href": "#xpointer(id('tok_71')/range-to(id('tok_72')))"}, {"@id": "lang_79", "@xlink:href": "#tok_79"}, {"@id": "lang_109", "@xlink:href": "#tok_109"}, {"@id": "lang_138", "@xlink:href": "#tok_138"}, {"@id": "lang_145", "@xlink:href": "#tok_145"}, {"@id": "lang_168", "@xlink:href": "#tok_168"}, {"@id": "lang_185", "@xlink:href": "#tok_185"}, {"@id": "lang_189", "@xlink:href": "#tok_189"}, {"@id": "lang_196", "@xlink:href": "#tok_196"}, {"@id": "lang_200", "@xlink:href": "#tok_200"}, {"@id": "lang_247", "@xlink:href": "#tok_247"}, {"@id": "lang_301", "@xlink:href": "#tok_301"}, {"@id": "lang_315", "@xlink:href": "#tok_315"}, {"@id": "lang_319", "@xlink:href": "#xpointer(id('tok_319')/range-to(id('tok_322')))"}, {"@id": "lang_328", "@xlink:href": "#tok_328"}, {"@id": "lang_355", "@xlink:href": "#xpointer(id('tok_355')/range-to(id('tok_356')))"}, {"@id": "lang_359", "@xlink:href": "#xpointer(id('tok_359')/range-to(id('tok_360')))"}, {"@id": "lang_369", "@xlink:href": "#tok_369"}, {"@id": "lang_399", "@xlink:href": "#xpointer(id('tok_399')/range-to(id('tok_400')))"}, {"@id": "lang_403", "@xlink:href": "#tok_403"}, {"@id": "lang_413", "@xlink:href": "#tok_413"}, {"@id": "lang_453", "@xlink:href": "#xpointer(id('tok_453')/range-to(id('tok_454')))"}, {"@id": "lang_472", "@xlink:href": "#xpointer(id('tok_472')/range-to(id('tok_473')))"}, {"@id": "lang_491", "@xlink:href": "#xpointer(id('tok_491')/range-to(id('tok_492')))"}, {"@id": "lang_495", "@xlink:href": "#xpointer(id('tok_495')/range-to(id('tok_496')))"}, {"@id": "lang_498", "@xlink:href": "#tok_498"}, {"@id": "lang_513", "@xlink:href": "#tok_513"}, {"@id": "lang_532", "@xlink:href": "#xpointer(id('tok_532')/range-to(id('tok_533')))"}, {"@id": "lang_549", "@xlink:href": "#tok_549"}, {"@id": "lang_560", "@xlink:href": "#tok_560"}, {"@id": "lang_571", "@xlink:href": "#tok_571"}, {"@id": "lang_590", "@xlink:href": "#xpointer(id('tok_590')/range-to(id('tok_591')))"}, {"@id": "lang_610", "@xlink:href": "#tok_610"}, {"@id": "lang_646", "@xlink:href": "#tok_646"}, {"@id": "lang_674", "@xlink:href": "#tok_674"}, {"@id": "lang_704", "@xlink:href": "#tok_704"}, {"@id": "lang_707", "@xlink:href": "#tok_707"}, {"@id": "lang_708", "@xlink:href": "#tok_708"}, {"@id": "lang_735", "@xlink:href": "#tok_735"}, {"@id": "lang_750", "@xlink:href": "#tok_750"}, {"@id": "lang_762", "@xlink:href": "#tok_762"}, {"@id": "lang_774", "@xlink:href": "#tok_774"}, {"@id": "lang_775", "@xlink:href": "#tok_775"}, {"@id": "lang_827", "@xlink:href": "#tok_827"}, {"@id": "lang_844", "@xlink:href": "#tok_844"}, {"@id": "lang_849", "@xlink:href": "#tok_849"}, {"@id": "lang_857", "@xlink:href": "#tok_857"}, {"@id": "lang_869", "@xlink:href": "#tok_869"}, {"@id": "lang_873", "@xlink:href": "#tok_873"}, {"@id": "lang_912", "@xlink:href": "#tok_912"}, {"@id": "lang_930", "@xlink:href": "#tok_930"}, {"@id": "lang_952", "@xlink:href": "#tok_952"}, {"@id": "lang_963", "@xlink:href": "#tok_963"}, {"@id": "lang_978", "@xlink:href": "#tok_978"}, {"@id": "lang_1017", "@xlink:href": "#tok_1017"}, {"@id": "lang_1022", "@xlink:href": "#tok_1022"}, {"@id": "lang_1032", "@xlink:href": "#xpointer(id('tok_1032')/range-to(id('tok_1033')))"}, {"@id": "lang_1042", "@xlink:href": "#xpointer(id('tok_1042')/range-to(id('tok_1043')))"}, {"@id": "lang_1071", "@xlink:href": "#xpointer(id('tok_1071')/range-to(id('tok_1072')))"}, {"@id": "lang_1075", "@xlink:href": "#xpointer(id('tok_1075')/range-to(id('tok_1076')))"}, {"@id": "lang_1113", "@xlink:href": "#xpointer(id('tok_1113')/range-to(id('tok_1114')))"}, {"@id": "lang_1120", "@xlink:href": "#tok_1120"}, {"@id": "lang_1124", "@xlink:href": "#xpointer(id('tok_1124')/range-to(id('tok_1125')))"}, {"@id": "lang_1133", "@xlink:href": "#tok_1133"}, {"@id": "lang_1146", "@xlink:href": "#tok_1146"}, {"@id": "lang_1169", "@xlink:href": "#tok_1169"}, {"@id": "lang_1173", "@xlink:href": "#xpointer(id('tok_1173')/range-to(id('tok_1176')))"}, {"@id": "lang_1187", "@xlink:href": "#tok_1187"}, {"@id": "lang_1191", "@xlink:href": "#tok_1191"}, {"@id": "lang_1202", "@xlink:href": "#tok_1202"}, {"@id": "lang_1208", "@xlink:href": "#tok_1208"}, {"@id": "lang_1228", "@xlink:href": "#xpointer(id('tok_1228')/range-to(id('tok_1229')))"}, {"@id": "lang_1249", "@xlink:href": "#xpointer(id('tok_1249')/range-to(id('tok_1250')))"}, {"@id": "lang_1254", "@xlink:href": "#tok_1254"}, {"@id": "lang_1269", "@xlink:href": "#tok_1269"}, {"@id": "lang_1274", "@xlink:href": "#xpointer(id('tok_1274')/range-to(id('tok_1275')))"}, {"@id": "lang_1280", "@xlink:href": "#tok_1280"}, {"@id": "lang_1307", "@xlink:href": "#tok_1307"}, {"@id": "lang_1333", "@xlink:href": "#tok_1333"}, {"@id": "lang_1345", "@xlink:href": "#xpointer(id('tok_1345')/range-to(id('tok_1346')))"}, {"@id": "lang_1354", "@xlink:href": "#tok_1354"}, {"@id": "lang_1397", "@xlink:href": "#tok_1397"}, {"@id": "lang_1424", "@xlink:href": "#tok_1424"}, {"@id": "lang_1428", "@xlink:href": "#tok_1428"}, {"@id": "lang_1440", "@xlink:href": "#tok_1440"}, {"@id": "lang_1442", "@xlink:href": "#xpointer(id('tok_1442')/range-to(id('tok_1443')))"}, {"@id": "lang_1446", "@xlink:href": "#xpointer(id('tok_1446')/range-to(id('tok_1447')))"}, {"@id": "lang_1458", "@xlink:href": "#tok_1458"}, {"@id": "lang_1478", "@xlink:href": "#tok_1478"}, {"@id": "lang_1492", "@xlink:href": "#tok_1492"}, {"@id": "lang_1526", "@xlink:href": "#xpointer(id('tok_1526')/range-to(id('tok_1527')))"}, {"@id": "lang_1536", "@xlink:href": "#tok_1536"}, {"@id": "lang_1547", "@xlink:href": "#tok_1547"}, {"@id": "lang_1642", "@xlink:href": "#tok_1642"}, {"@id": "lang_1663", "@xlink:href": "#tok_1663"}, {"@id": "lang_1664", "@xlink:href": "#tok_1664"}, {"@id": "lang_1683", "@xlink:href": "#xpointer(id('tok_1683')/range-to(id('tok_1684')))"}, {"@id": "lang_1694", "@xlink:href": "#tok_1694"}, {"@id": "lang_1707", "@xlink:href": "#tok_1707"}, {"@id": "lang_1714", "@xlink:href": "#xpointer(id('tok_1714')/range-to(id('tok_1715')))"}, {"@id": "lang_1726", "@xlink:href": "#tok_1726"}, {"@id": "lang_1756", "@xlink:href": "#tok_1756"}, {"@id": "lang_1776", "@xlink:href": "#tok_1776"}, {"@id": "lang_1853", "@xlink:href": "#tok_1853"}, {"@id": "lang_1854", "@xlink:href": "#tok_1854"}, {"@id": "lang_1860", "@xlink:href": "#tok_1860"}, {"@id": "lang_1888", "@xlink:href": "#xpointer(id('tok_1888')/range-to(id('tok_1889')))"}, {"@id": "lang_1891", "@xlink:href": "#tok_1891"}, {"@id": "lang_1953", "@xlink:href": "#xpointer(id('tok_1953')/range-to(id('tok_1954')))"}, {"@id": "lang_1956", "@xlink:href": "#tok_1956"}, {"@id": "lang_1958", "@xlink:href": "#xpointer(id('tok_1958')/range-to(id('tok_1959')))"}, {"@id": "lang_2042", "@xlink:href": "#tok_2042"}, {"@id": "lang_2094", "@xlink:href": "#tok_2094"}, {"@id": "lang_2149", "@xlink:href": "#tok_2149"}, {"@id": "lang_2177", "@xlink:href": "#tok_2177"}, {"@id": "lang_2179", "@xlink:href": "#tok_2179"}, {"@id": "lang_2186", "@xlink:href": "#tok_2186"}, {"@id": "lang_2199", "@xlink:href": "#tok_2199"}, {"@id": "lang_2205", "@xlink:href": "#tok_2205"}, {"@id": "lang_2230", "@xlink:href": "#tok_2230"}, {"@id": "lang_2237", "@xlink:href": "#tok_2237"}, {"@id": "lang_2256", "@xlink:href": "#tok_2256"}, {"@id": "lang_2257", "@xlink:href": "#tok_2257"}, {"@id": "lang_2266", "@xlink:href": "#tok_2266"}, {"@id": "lang_2272", "@xlink:href": "#tok_2272"}, {"@id": "lang_2278", "@xlink:href": "#xpointer(id('tok_2278')/range-to(id('tok_2279')))"}, {"@id": "lang_2292", "@xlink:href": "#tok_2292"}, {"@id": "lang_2307", "@xlink:href": "#xpointer(id('tok_2307')/range-to(id('tok_2308')))"}, {"@id": "lang_2340", "@xlink:href": "#tok_2340"}, {"@id": "lang_2348", "@xlink:href": "#tok_2348"}, {"@id": "lang_2354", "@xlink:href": "#xpointer(id('tok_2354')/range-to(id('tok_2357')))"}, {"@id": "lang_2364", "@xlink:href": "#tok_2364"}, {"@id": "lang_2402", "@xlink:href": "#tok_2402"}, {"@id": "lang_2423", "@xlink:href": "#tok_2423"}, {"@id": "lang_2432", "@xlink:href": "#tok_2432"}, {"@id": "lang_2453", "@xlink:href": "#tok_2453"}, {"@id": "lang_2461", "@xlink:href": "#tok_2461"}, {"@id": "lang_2464", "@xlink:href": "#tok_2464"}, {"@id": "lang_2482", "@xlink:href": "#tok_2482"}, {"@id": "lang_2487", "@xlink:href": "#tok_2487"}, {"@id": "lang_2494", "@xlink:href": "#xpointer(id('tok_2494')/range-to(id('tok_2495')))"}, {"@id": "lang_2529", "@xlink:href": "#xpointer(id('tok_2529')/range-to(id('tok_2530')))"}, {"@id": "lang_2550", "@xlink:href": "#tok_2550"}, {"@id": "lang_2577", "@xlink:href": "#tok_2577"}, {"@id": "lang_2579", "@xlink:href": "#tok_2579"}, {"@id": "lang_2589", "@xlink:href": "#tok_2589"}, {"@id": "lang_2590", "@xlink:href": "#xpointer(id('tok_2590')/range-to(id('tok_2591')))"}, {"@id": "lang_2627", "@xlink:href": "#tok_2627"}, {"@id": "lang_2639", "@xlink:href": "#tok_2639"}, {"@id": "lang_2659", "@xlink:href": "#xpointer(id('tok_2659')/range-to(id('tok_2660')))"}, {"@id": "lang_2695", "@xlink:href": "#tok_2695"}, {"@id": "lang_2744", "@xlink:href": "#xpointer(id('tok_2744')/range-to(id('tok_2745')))"}, {"@id": "lang_2746", "@xlink:href": "#tok_2746"}, {"@id": "lang_2756", "@xlink:href": "#tok_2756"}, {"@id": "lang_2781", "@xlink:href": "#tok_2781"}, {"@id": "lang_2809", "@xlink:href": "#tok_2809"}]}}}