{"paula": {"@version": "1.0", "header": {"@paula_id": "shenoute.fox_hi_rend"}, "featList": {"@xmlns:xlink": "http://www.w3.org/1999/xlink", "@type": "hi_rend", "@xml:base": "shenoute.fox.hi_rendSeg.xml", "feat": [{"@xlink:href": "#hi_rend_2", "@value": "ekthetic"}, {"@xlink:href": "#hi_rend_182", "@value": "ekthetic"}, {"@xlink:href": "#hi_rend_216", "@value": "second ni superfluous/error because of line break?"}, {"@xlink:href": "#hi_rend_320", "@value": "superscript above simma"}, {"@xlink:href": "#hi_rend_321", "@value": "subscript under omicron"}, {"@xlink:href": "#hi_rend_327", "@value": "ekthetic"}, {"@xlink:href": "#hi_rend_438", "@value": "ekthetic"}, {"@xlink:href": "#hi_rend_774", "@value": "ekthetic"}, {"@xlink:href": "#hi_rend_1080", "@value": "ekthetic"}, {"@xlink:href": "#hi_rend_1174", "@value": "superscript above simma"}, {"@xlink:href": "#hi_rend_1175", "@value": "subscript under omicron"}, {"@xlink:href": "#hi_rend_1209", "@value": "ekthetic"}, {"@xlink:href": "#hi_rend_1628", "@value": "ekthetic"}, {"@xlink:href": "#hi_rend_1744", "@value": "ekthetic"}, {"@xlink:href": "#hi_rend_1918", "@value": "ekthetic"}, {"@xlink:href": "#hi_rend_1941", "@value": "superscript above sigma"}, {"@xlink:href": "#hi_rend_1942", "@value": "subscript below omicron"}, {"@xlink:href": "#hi_rend_2053", "@value": "ekthetic"}, {"@xlink:href": "#hi_rend_2292", "@value": "ekthetic"}, {"@xlink:href": "#hi_rend_2355", "@value": "superscript above sigma"}, {"@xlink:href": "#hi_rend_2356", "@value": "subscript below omicron"}, {"@xlink:href": "#hi_rend_2372", "@value": "ekthetic"}, {"@xlink:href": "#hi_rend_2395", "@value": "one space right"}, {"@xlink:href": "#hi_rend_2411", "@value": "one space right"}, {"@xlink:href": "#hi_rend_2426", "@value": "one space right"}, {"@xlink:href": "#hi_rend_2439", "@value": "one space right"}, {"@xlink:href": "#hi_rend_2491", "@value": "ekthetic"}, {"@xlink:href": "#hi_rend_2531", "@value": "one space right"}, {"@xlink:href": "#hi_rend_2558", "@value": "one space right"}, {"@xlink:href": "#hi_rend_2569", "@value": "one space right"}, {"@xlink:href": "#hi_rend_2592", "@value": "one space right"}, {"@xlink:href": "#hi_rend_2626", "@value": "one space right"}, {"@xlink:href": "#hi_rend_2638", "@value": "one space right"}, {"@xlink:href": "#hi_rend_2674", "@value": "one space right"}, {"@xlink:href": "#hi_rend_2709", "@value": "ekthetic"}, {"@xlink:href": "#hi_rend_2735", "@value": "one space right"}, {"@xlink:href": "#hi_rend_2742", "@value": "one space right"}]}}}